beancount_sog/__init__.py
beancount_sog-0.1.1.dist-info/METADATA
beancount_sog-0.1.1.dist-info/WHEEL
beancount_sog-0.1.1.dist-info/RECORD
